hypershot/__init__.py
hypershot/cli.py
hypershot/config.py
hypershot/handlers.py
hypershot/image.py
hypershot/templating.py
hypershot/util.py
hypershot/video.py
hypershot/data/templates/bbcode.j2
hypershot/data/templates/json.j2
hypershot/data/templates/links.j2
hypershot/data/templates/plain.j2
hypershot/data/templates/yaml.j2
hypershot-0.3.1.data/data/EGG-INFO/CHANGES.rst
hypershot-0.3.1.data/data/EGG-INFO/LICENSE
hypershot-0.3.1.data/data/EGG-INFO/README.md
hypershot-0.3.1.dist-info/DESCRIPTION.rst
hypershot-0.3.1.dist-info/METADATA
hypershot-0.3.1.dist-info/RECORD
hypershot-0.3.1.dist-info/WHEEL
hypershot-0.3.1.dist-info/entry_points.txt
hypershot-0.3.1.dist-info/metadata.json
hypershot-0.3.1.dist-info/top_level.txt
hypershot-0.3.1.dist-info/zip-safe
