Metadata-Version: 2.0
Name: hypershot
Version: 0.3.1
Summary: Create screen shots of a video file, and upload them to an image host.
Home-page: https://gitlab.com/kybernetics/hypershot
Author: Automan
Author-email: automan@protonmail.ch
License: MIT
Keywords: screenshot,mplayer,ffmpeg
Platform: UNKNOWN
Classifier: Development Status :: 4 - Beta
Classifier: Environment :: Console
Classifier: Intended Audience :: End Users/Desktop
Classifier: License :: OSI Approved :: MIT License
Classifier: Operating System :: POSIX :: Linux
Classifier: Programming Language :: Python :: 3 :: Only
Classifier: Programming Language :: Python :: 3.4
Classifier: Topic :: Multimedia :: Graphics :: Capture
Classifier: Topic :: Multimedia :: Video
Requires-Dist: Jinja2
Requires-Dist: PyYAML
Requires-Dist: addict
Requires-Dist: appdirs
Requires-Dist: better-exceptions
Requires-Dist: colorama
Requires-Dist: docopt
Requires-Dist: imgurpython
Requires-Dist: requests
Requires-Dist: requests-toolbelt
Requires-Dist: terminaltables
Requires-Dist: tqdm
